jsp_benchmarks/__init__.py
jsp_benchmarks/instance_loader.py
jsp_benchmarks/instance_meta_data.json
jsp_benchmarks/instances/abz5
jsp_benchmarks/instances/abz6
jsp_benchmarks/instances/abz7
jsp_benchmarks/instances/abz8
jsp_benchmarks/instances/abz9
jsp_benchmarks/instances/ft06
jsp_benchmarks/instances/ft10
jsp_benchmarks/instances/ft20
jsp_benchmarks/instances/la01
jsp_benchmarks/instances/la02
jsp_benchmarks/instances/la03
jsp_benchmarks/instances/la04
jsp_benchmarks/instances/la05
jsp_benchmarks/instances/la06
jsp_benchmarks/instances/la07
jsp_benchmarks/instances/la08
jsp_benchmarks/instances/la09
jsp_benchmarks/instances/la10
jsp_benchmarks/instances/la11
jsp_benchmarks/instances/la12
jsp_benchmarks/instances/la13
jsp_benchmarks/instances/la14
jsp_benchmarks/instances/la15
jsp_benchmarks/instances/la16
jsp_benchmarks/instances/la17
jsp_benchmarks/instances/la18
jsp_benchmarks/instances/la19
jsp_benchmarks/instances/la20
jsp_benchmarks/instances/la21
jsp_benchmarks/instances/la22
jsp_benchmarks/instances/la23
jsp_benchmarks/instances/la24
jsp_benchmarks/instances/la25
jsp_benchmarks/instances/la26
jsp_benchmarks/instances/la27
jsp_benchmarks/instances/la28
jsp_benchmarks/instances/la29
jsp_benchmarks/instances/la30
jsp_benchmarks/instances/la31
jsp_benchmarks/instances/la32
jsp_benchmarks/instances/la33
jsp_benchmarks/instances/la34
jsp_benchmarks/instances/la35
jsp_benchmarks/instances/la36
jsp_benchmarks/instances/la37
jsp_benchmarks/instances/la38
jsp_benchmarks/instances/la39
jsp_benchmarks/instances/la40
jsp_benchmarks/instances/orb01
jsp_benchmarks/instances/orb02
jsp_benchmarks/instances/orb03
jsp_benchmarks/instances/orb04
jsp_benchmarks/instances/orb05
jsp_benchmarks/instances/orb06
jsp_benchmarks/instances/orb07
jsp_benchmarks/instances/orb08
jsp_benchmarks/instances/orb09
jsp_benchmarks/instances/orb10
jsp_benchmarks/instances/suwa
jsp_benchmarks/instances/swv01
jsp_benchmarks/instances/swv02
jsp_benchmarks/instances/swv03
jsp_benchmarks-0.1.83.dist-info/WHEEL
jsp_benchmarks-0.1.83.dist-info/METADATA
jsp_benchmarks-0.1.83.dist-info/RECORD
