Metadata-Version: 2.1
Name: jsp-benchmarks
Version: 0.1.83
Summary: ジョブショップスケジューリング問題のベンチマーク問題をpythonのクラスで表現し，load出来るようにする
Home-page: https://github.com/tkp0331/jsp-benckmarks
Author: 鈴木貴大
Author-email: merioda.seven.24@gmail.com
Requires-Python: >=3.8.3,<4.0.0
Classifier: Programming Language :: Python :: 3
Classifier: Programming Language :: Python :: 3.10
Classifier: Programming Language :: Python :: 3.9
Requires-Dist: jsp-exp (>=0.1.31,<0.2.0)
Project-URL: Repository, https://github.com/tkp0331/jsp-benckmarks
